pytropical/__init__.py
pytropical/_version.py
pytropical/tropical_algebra.py
pytropical/utils.py
pytropical-0.0.2.dist-info/LICENSE.txt
pytropical-0.0.2.dist-info/METADATA
pytropical-0.0.2.dist-info/WHEEL
pytropical-0.0.2.dist-info/top_level.txt
pytropical-0.0.2.dist-info/RECORD
